megatron/bridge/__init__.py
megatron/bridge/package_info.py
megatron/bridge/data/__init__.py
megatron/bridge/data/loaders.py
megatron/bridge/data/samplers.py
megatron/bridge/data/utils.py
megatron/bridge/data/builders/__init__.py
megatron/bridge/data/builders/finetuning_dataset.py
megatron/bridge/data/builders/hf_dataset.py
megatron/bridge/data/datasets/__init__.py
megatron/bridge/data/datasets/packed_sequence.py
megatron/bridge/data/datasets/packing_utils.py
megatron/bridge/data/datasets/sft.py
megatron/bridge/data/datasets/utils.py
megatron/bridge/data/hf_processors/__init__.py
megatron/bridge/data/hf_processors/squad.py
megatron/bridge/models/__init__.py
megatron/bridge/models/config.py
megatron/bridge/models/gpt_full_te_layer_autocast_spec.py
megatron/bridge/models/gpt_provider.py
megatron/bridge/models/model_provider.py
megatron/bridge/models/t5_provider.py
megatron/bridge/models/transformer_config.py
megatron/bridge/models/conversion/__init__.py
megatron/bridge/models/conversion/auto_bridge.py
megatron/bridge/models/conversion/mapping_registry.py
megatron/bridge/models/conversion/model_bridge.py
megatron/bridge/models/conversion/param_mapping.py
megatron/bridge/models/conversion/utils.py
megatron/bridge/models/decorators/__init__.py
megatron/bridge/models/decorators/dispatch.py
megatron/bridge/models/decorators/torchrun.py
megatron/bridge/models/deepseek/__init__.py
megatron/bridge/models/deepseek/common.py
megatron/bridge/models/deepseek/deepseek_provider.py
megatron/bridge/models/deepseek/deepseek_v2_bridge.py
megatron/bridge/models/deepseek/deepseek_v3_bridge.py
megatron/bridge/models/hf_pretrained/__init__.py
megatron/bridge/models/hf_pretrained/base.py
megatron/bridge/models/hf_pretrained/causal_lm.py
megatron/bridge/models/hf_pretrained/safe_config_loader.py
megatron/bridge/models/hf_pretrained/state.py
megatron/bridge/models/hf_pretrained/vlm.py
megatron/bridge/models/llama/__init__.py
megatron/bridge/models/llama/llama4_utils.py
megatron_bridge-0.2.0rc5.dist-info/licenses/LICENSE
megatron_bridge-0.2.0rc5.dist-info/METADATA
megatron_bridge-0.2.0rc5.dist-info/WHEEL
megatron_bridge-0.2.0rc5.dist-info/entry_points.txt
megatron_bridge-0.2.0rc5.dist-info/top_level.txt
megatron_bridge-0.2.0rc5.dist-info/RECORD
