Metadata-Version: 2.4
Name: megatron-bridge
Version: 0.2.0rc5
Summary: Megatron Bridge: Training Recipes for Megatron-based LLM and VLM models
Author-email: NVIDIA <nemo-toolkit@nvidia.com>
Maintainer-email: NVIDIA <nemo-toolkit@nvidia.com>
License:                                  Apache License
Project-URL: Download, https://github.com/NVIDIA-NeMo/Megatron-Bridge/releases
Project-URL: Homepage, https://github.com/NVIDIA-NeMo/Megatron-Bridge
Keywords: NLP,NeMo,deep,gpu,language,learning,machine,nvidia,pytorch,speech,torch,tts
Classifier: Development Status :: 5 - Production/Stable
Classifier: Environment :: Console
Classifier: Intended Audience :: Developers
Classifier: Intended Audience :: Information Technology
Classifier: Intended Audience :: Science/Research
Classifier: License :: OSI Approved :: Apache Software License
Classifier: Natural Language :: English
Classifier: Operating System :: OS Independent
Classifier: Programming Language :: Python :: 3
Classifier: Programming Language :: Python :: 3.10
Classifier: Topic :: Scientific/Engineering :: Artificial Intelligence
Classifier: Topic :: Scientific/Engineering :: Image Recognition
Classifier: Topic :: Scientific/Engineering :: Mathematics
Classifier: Topic :: Scientific/Engineering
Classifier: Topic :: Software Development :: Libraries :: Python Modules
Classifier: Topic :: Software Development :: Libraries
Classifier: Topic :: Utilities
Requires-Python: >=3.10
License-File: LICENSE
Requires-Dist: datasets
Requires-Dist: omegaconf>=2.3.0
Requires-Dist: tensorboard>=2.19.0
Requires-Dist: typing-extensions
Requires-Dist: rich
Requires-Dist: wandb>=0.19.10
Requires-Dist: six>=1.17.0
Requires-Dist: regex>=2024.11.6
Requires-Dist: pyyaml>=6.0.2
Requires-Dist: tqdm>=4.67.1
Requires-Dist: hydra-core<=1.3.2,>1.3
Requires-Dist: megatron-core[dev,mlm]<0.16.0,>=0.14.0a0
Provides-Extra: recipes
Requires-Dist: nemo-run<0.6.0,>=0.5.0a0; extra == "recipes"
Dynamic: license-file
